hil/can/zlg/__init__.py
hil/can/zlg/bus.py
hil/can/zlg/zlgcan.dll
hil/can/zlg/zlgcan.py
python_can_zlg-0.0.1.dist-info/LICENSE
python_can_zlg-0.0.1.dist-info/METADATA
python_can_zlg-0.0.1.dist-info/WHEEL
python_can_zlg-0.0.1.dist-info/entry_points.txt
python_can_zlg-0.0.1.dist-info/top_level.txt
python_can_zlg-0.0.1.dist-info/RECORD
