Metadata-Version: 2.1
Name: python-can-zlg
Version: 0.0.1
Summary: 周立功CAN的python-can扩展
Author: notmmao
Author-email: notmmao@gmail.com
License: MIT
Platform: windows
Requires-Python: >=3.7
License-File: LICENSE
Requires-Dist: python-can (>=3.0.0)
Requires-Dist: python-can-zlg-kerneldlls
